Workbook

Sheet Cover
A1: INSITE Standard Discounted Cash Flow & Bulk Sale Analysis Workbook
A3: Workbook Publication | B3: INS-102A
A4: Workbook Version | B4: Version 1.0
A5: Prepared For | B5: INSITE Development Impact & School Fee Financing Program
A6: Program Administrator | B6: HGF Management Company
A7: Workbook Purpose | B7: Standardized DCF and Bulk Sale Analysis for INSITE appraisal assignments
A8: Property Name
A9: County
A10: Appraiser
A11: Effective Date of Value
A12: Report Date
A13: Reviewed By
A14: Revision Notes
A16: This workbook is intended to standardize the presentation and calculation of discounted cash flow and bulk sale analyses for INSITE appraisal assignments. The appraiser remains responsible for selecting and supporting all inputs, assumptions, and conclusions in accordance with USPAP, CDIAC guidance, and the INSITE Appraisal Standards Manual.

Sheet Instructions
A1: Workbook Instructions
A3: Use this workbook when a Bulk Sale Analysis and/or Discounted Cash Flow analysis is required under Chapter 8 of the INSITE Appraisal Standards Manual.
A5: Color Conventions
A6: Color / Font | B6: Meaning | C6: User Action | D6: Notes
A7: Yellow fill + blue font | B7: Hardcoded input | C7: Enter or update | D7: Assumptions must be supported by market evidence.
A8: Gray fill + black font | B8: Formula / calculation | C8: Do not overwrite | D8: Formula cells are intended to remain protected.
A9: Green font | B9: Linked value from another sheet | C9: Review only | D9: Trace back to source sheet for support.
A10: Forest green header | B10: Section heading | C10: N/A | D10: Standard INSITE format.
A12: Required Workflow
A13: Step 1 | B13: Complete Property Info.
A14: Step 2 | B14: Enter Market Assumptions with source/support notes.
A15: Step 3 | B15: Enter remaining development, soft, holding, and selling costs.
A16: Step 4 | B16: Complete Discount Rate Support.
A17: Step 5 | B17: Review Absorption Schedule and DCF Model.
A18: Step 6 | B18: Review Bulk Sale Analysis and Sensitivity Tables.
A19: Step 7 | B19: Copy Report Exhibits into the appraisal report.
A20: Step 8 | B20: Submit workbook with appraisal report and retain in workfile.

Sheet Property Info
A1: Property Information
A3: Input | B3: Value | C3: Source / Support | D3: Notes
A4: Property Name
A5: County
A6: City
A7: Effective Date of Value | B7: 46210 | C7: Appraisal engagement / inspection date
A8: Appraiser
A9: APNs | D9: List all parcels included.
A10: Current Owner
A11: Gross Acres | B11: 0
A12: Net Developable Acres | B12: 0
A13: Total Lots / Units | B13: 0 | D13: Used as beginning inventory.
A14: Current Development Stage | D14: Raw, entitled, mass graded, blue-top, finished lots, etc.
A15: Highest & Best Use
A16: Zoning
A17: General Plan / Specific Plan
A18: Existing CFDs / Assessments

Sheet Market Assumptions
A1: Market Assumptions
A3: Assumption | B3: Input | C3: Unit / Format | D3: Source / Support
A4: Beginning Lot / Unit Sale Price | B4: 0 | C4: $ / lot
A5: Annual Price Appreciation | B5: 0 | C5: %
A6: Monthly Absorption | B6: 0 | C6: lots / month
A7: Marketing & Selling Cost | B7: 0 | C7: % of gross revenue
A8: Developer Profit / Incentive | B8: 0 | C8: % of gross revenue
A9: Builder Incentives | B9: 0 | C9: $ / lot or % if separately modeled
A10: Development Cost Period | B10: 12 | C10: months
A11: Soft Cost Period | B11: 12 | C11: months
A12: Analysis Period | B12: 60 | C12: months | D12: Workbook model currently supports 60 months.
A13: Cash Flow Frequency | B13: Monthly | C13: Monthly
A14: Primary Market Evidence | C14: Text
A15: Market Risk Notes | C15: Text

Sheet Development Costs
A1: Development Costs
A3: Remaining Hard Costs
A4: Cost Item | B4: Amount | C4: Timing / Notes | D4: Source / Support
A5: Onsite Improvements | B5: 0
A6: Offsite Improvements | B6: 0
A7: Utilities | B7: 0
A8: Grading | B8: 0
A9: Storm Drain / Drainage | B9: 0
A10: Roads / Curbs / Gutters | B10: 0
A11: Contingency | B11: 0
A12: Other Hard Costs | B12: 0
A14: Total Remaining Hard Costs | B14: =SUM(B5:B12) -> 0
A17: Remaining Soft Costs
A18: Cost Item | B18: Amount | C18: Timing / Notes | D18: Source / Support
A19: Engineering | B19: 0
A20: Surveying | B20: 0
A21: Architecture / Planning | B21: 0
A22: Permitting | B22: 0
A23: Legal / Administrative | B23: 0
A24: Environmental | B24: 0
A25: Other Soft Costs | B25: 0
A26: Total Remaining Soft Costs | B26: =SUM(B19:B25) -> 0

Sheet Holding Costs
A1: Monthly Holding Costs
A3: Cost Item | B3: Monthly Amount | C3: Notes | D3: Source / Support
A4: Property Taxes | B4: 0
A5: Insurance | B5: 0
A6: HOA / Maintenance | B6: 0
A7: Utilities | B7: 0
A8: Security | B8: 0
A9: Administrative | B9: 0
A10: Other Carrying Costs | B10: 0
A12: Total Monthly Holding Costs | B12: =SUM(B4:B10) -> 0
A13: Annualized Holding Costs | B13: =B12*12 -> 0
A14: Holding Cost per Lot / Month | B14: =IF('Property Info'!B12>0,B12/'Property Info'!B12,0) -> 0

Sheet Discount Rate Support
A1: Discount Rate Support
A3: Component | B3: Assessment | C3: Premium / Rate | D3: Support / Source | E3: Notes
A4: Base Required Return | B4: Market input | C4: 0 | E4: Base rate before property-specific risk premiums.
A5: Market Risk | B5: Select | C5: 0
A6: Absorption Risk | B6: Select | C6: 0
A7: Entitlement Risk | B7: Select | C7: 0
A8: Development / Infrastructure Risk | B8: Select | C8: 0
A9: Competition / Supply Risk | B9: Select | C9: 0
A10: Project Size / Liquidity Risk | B10: Select | C10: 0
A11: Financing Environment | B11: Select | C11: 0
A12: Other Risk Adjustment | B12: Input | C12: 0
A13: Selected Discount Rate | C13: =SUM(C4:C12) -> 0

Sheet Absorption Schedule
A1: Absorption Schedule
A3: Month | B3: Month End | C3: Beginning Inventory | D3: Lots Sold | E3: Ending Inventory | F3: Average Sale Price | G3: Gross Revenue | H3: Source / Notes
A4: 1 | B4: =EOMONTH('Property Info'!$B$7,A4-1) -> 46234 | C4: ='Property Info'!$B$12 -> 0 | D4: =MIN('Market Assumptions'!$B$6,C4) -> 0 | E4: =MAX(C4-D4,0) -> 0 | F4: ='Market Assumptions'!$B$4*(1+'Market Assumptions'!$B$5/12)^(A4-1) -> 0 | G4: =D4*F4 -> 0
A5: 2 | B5: =EOMONTH('Property Info'!$B$7,A5-1) -> 46265 | C5: =E4 -> 0 | D5: =MIN('Market Assumptions'!$B$6,C5) -> 0 | E5: =MAX(C5-D5,0) -> 0 | F5: ='Market Assumptions'!$B$4*(1+'Market Assumptions'!$B$5/12)^(A5-1) -> 0 | G5: =D5*F5 -> 0
A6: 3 | B6: =EOMONTH('Property Info'!$B$7,A6-1) -> 46295 | C6: =E5 -> 0 | D6: =MIN('Market Assumptions'!$B$6,C6) -> 0 | E6: =MAX(C6-D6,0) -> 0 | F6: ='Market Assumptions'!$B$4*(1+'Market Assumptions'!$B$5/12)^(A6-1) -> 0 | G6: =D6*F6 -> 0
A7: 4 | B7: =EOMONTH('Property Info'!$B$7,A7-1) -> 46326 | C7: =E6 -> 0 | D7: =MIN('Market Assumptions'!$B$6,C7) -> 0 | E7: =MAX(C7-D7,0) -> 0 | F7: ='Market Assumptions'!$B$4*(1+'Market Assumptions'!$B$5/12)^(A7-1) -> 0 | G7: =D7*F7 -> 0
A8: 5 | B8: =EOMONTH('Property Info'!$B$7,A8-1) -> 46356 | C8: =E7 -> 0 | D8: =MIN('Market Assumptions'!$B$6,C8) -> 0 | E8: =MAX(C8-D8,0) -> 0 | F8: ='Market Assumptions'!$B$4*(1+'Market Assumptions'!$B$5/12)^(A8-1) -> 0 | G8: =D8*F8 -> 0
A9: 6 | B9: =EOMONTH('Property Info'!$B$7,A9-1) -> 46387 | C9: =E8 -> 0 | D9: =MIN('Market Assumptions'!$B$6,C9) -> 0 | E9: =MAX(C9-D9,0) -> 0 | F9: ='Market Assumptions'!$B$4*(1+'Market Assumptions'!$B$5/12)^(A9-1) -> 0 | G9: =D9*F9 -> 0
A10: 7 | B10: =EOMONTH('Property Info'!$B$7,A10-1) -> 46418 | C10: =E9 -> 0 | D10: =MIN('Market Assumptions'!$B$6,C10) -> 0 | E10: =MAX(C10-D10,0) -> 0 | F10: ='Market Assumptions'!$B$4*(1+'Market Assumptions'!$B$5/12)^(A10-1) -> 0 | G10: =D10*F10 -> 0
A11: 8 | B11: =EOMONTH('Property Info'!$B$7,A11-1) -> 46446 | C11: =E10 -> 0 | D11: =MIN('Market Assumptions'!$B$6,C11) -> 0 | E11: =MAX(C11-D11,0) -> 0 | F11: ='Market Assumptions'!$B$4*(1+'Market Assumptions'!$B$5/12)^(A11-1) -> 0 | G11: =D11*F11 -> 0
A12: 9 | B12: =EOMONTH('Property Info'!$B$7,A12-1) -> 46477 | C12: =E11 -> 0 | D12: =MIN('Market Assumptions'!$B$6,C12) -> 0 | E12: =MAX(C12-D12,0) -> 0 | F12: ='Market Assumptions'!$B$4*(1+'Market Assumptions'!$B$5/12)^(A12-1) -> 0 | G12: =D12*F12 -> 0
A13: 10 | B13: =EOMONTH('Property Info'!$B$7,A13-1) -> 46507 | C13: =E12 -> 0 | D13: =MIN('Market Assumptions'!$B$6,C13) -> 0 | E13: =MAX(C13-D13,0) -> 0 | F13: ='Market Assumptions'!$B$4*(1+'Market Assumptions'!$B$5/12)^(A13-1) -> 0 | G13: =D13*F13 -> 0
A14: 11 | B14: =EOMONTH('Property Info'!$B$7,A14-1) -> 46538 | C14: =E13 -> 0 | D14: =MIN('Market Assumptions'!$B$6,C14) -> 0 | E14: =MAX(C14-D14,0) -> 0 | F14: ='Market Assumptions'!$B$4*(1+'Market Assumptions'!$B$5/12)^(A14-1) -> 0 | G14: =D14*F14 -> 0
A15: 12 | B15: =EOMONTH('Property Info'!$B$7,A15-1) -> 46568 | C15: =E14 -> 0 | D15: =MIN('Market Assumptions'!$B$6,C15) -> 0 | E15: =MAX(C15-D15,0) -> 0 | F15: ='Market Assumptions'!$B$4*(1+'Market Assumptions'!$B$5/12)^(A15-1) -> 0 | G15: =D15*F15 -> 0
A16: 13 | B16: =EOMONTH('Property Info'!$B$7,A16-1) -> 46599 | C16: =E15 -> 0 | D16: =MIN('Market Assumptions'!$B$6,C16) -> 0 | E16: =MAX(C16-D16,0) -> 0 | F16: ='Market Assumptions'!$B$4*(1+'Market Assumptions'!$B$5/12)^(A16-1) -> 0 | G16: =D16*F16 -> 0
... A63: 60 | B63: =EOMONTH('Property Info'!$B$7,A63-1) -> 48029 | C63: =E62 -> 0 | D63: =MIN('Market Assumptions'!$B$6,C63) -> 0 | E63: =MAX(C63-D63,0) -> 0 | F63: ='Market Assumptions'!$B$4*(1+'Market Assumptions'!$B$5/12)^(A63-1) -> 0 | G63: =D63*F63 -> 0

Sheet DCF Model
A1: Discounted Cash Flow Model
A3: Line Item | B3: 1 | C3: 2 | D3: 3 | E3: 4 | F3: 5 | G3: 6 | H3: 7 | I3: 8 | J3: 9 | K3: 10 | L3: 11 | M3: 12 | N3: 13 | O3: 14 | P3: 15 | Q3: 16 | R3: 17 | S3: 18 | T3: 19 | U3: 20 | V3: 21 | W3: 22 | X3: 23 | Y3: 24 | Z3: 25 | AA3: 26 | AB3: 27 | AC3: 28 | AD3: 29 | AE3: 30 | AF3: 31 | AG3: 32 | AH3: 33 | AI3: 34 | AJ3: 35 | AK3: 36 | AL3: 37 | AM3: 38 | AN3: 39 | AO3: 40 | AP3: 41 | AQ3: 42 | AR3: 43 | AS3: 44 | AT3: 45 | AU3: 46 | AV3: 47 | AW3: 48 | AX3: 49 | AY3: 50 | AZ3: 51 | BA3: 52 | BB3: 53 | BC3: 54 | BD3: 55 | BE3: 56 | BF3: 57 | BG3: 58 | BH3: 59 | BI3: 60
A4: Gross Revenue | B4: ='Absorption Schedule'!G4 -> 0 | C4: ='Absorption Schedule'!G5 -> 0 | D4: ='Absorption Schedule'!G6 -> 0 | E4: ='Absorption Schedule'!G7 -> 0 | F4: ='Absorption Schedule'!G8 -> 0 | G4: ='Absorption Schedule'!G9 -> 0 | H4: ='Absorption Schedule'!G10 -> 0 | I4: ='Absorption Schedule'!G11 -> 0 | J4: ='Absorption Schedule'!G12 -> 0 | K4: ='Absorption Schedule'!G13 -> 0 | L4: ='Absorption Schedule'!G14 -> 0 | M4: ='Absorption Schedule'!G15 -> 0 | N4: ='Absorption Schedule'!G16 -> 0 | O4: ='Absorption Schedule'!G17 -> 0 | P4: ='Absorption Schedule'!G18 -> 0 | Q4: ='Absorption Schedule'!G19 -> 0 | R4: ='Absorption Schedule'!G20 -> 0 | S4: ='Absorption Schedule'!G21 -> 0 | T4: ='Absorption Schedule'!G22 -> 0 | U4: ='Absorption Schedule'!G23 -> 0 | V4: ='Absorption Schedule'!G24 -> 0 | W4: ='Absorption Schedule'!G25 -> 0 | X4: ='Absorption Schedule'!G26 -> 0 | Y4: ='Absorption Schedule'!G27 -> 0 | Z4: ='Absorption Schedule'!G28 -> 0 | AA4: ='Absorption Schedule'!G29 -> 0 | AB4: ='Absorption Schedule'!G30 -> 0 | AC4: ='Absorption Schedule'!G31 -> 0 | AD4: ='Absorption Schedule'!G32 -> 0 | AE4: ='Absorption Schedule'!G33 -> 0 | AF4: ='Absorption Schedule'!G34 -> 0 | AG4: ='Absorption Schedule'!G35 -> 0 | AH4: ='Absorption Schedule'!G36 -> 0 | AI4: ='Absorption Schedule'!G37 -> 0 | AJ4: ='Absorption Schedule'!G38 -> 0 | AK4: ='Absorption Schedule'!G39 -> 0 | AL4: ='Absorption Schedule'!G40 -> 0 | AM4: ='Absorption Schedule'!G41 -> 0 | AN4: ='Absorption Schedule'!G42 -> 0 | AO4: ='Absorption Schedule'!G43 -> 0 | AP4: ='Absorption Schedule'!G44 -> 0 | AQ4: ='Absorption Schedule'!G45 -> 0 | AR4: ='Absorption Schedule'!G46 -> 0 | AS4: ='Absorption Schedule'!G47 -> 0 | AT4: ='Absorption Schedule'!G48 -> 0 | AU4: ='Absorption Schedule'!G49 -> 0 | AV4: ='Absorption Schedule'!G50 -> 0 | AW4: ='Absorption Schedule'!G51 -> 0 | AX4: ='Absorption Schedule'!G52 -> 0 | AY4: ='Absorption Schedule'!G53 -> 0 | AZ4: ='Absorption Schedule'!G54 -> 0 | BA4: ='Absorption Schedule'!G55 -> 0 | BB4: ='Absorption Schedule'!G56 -> 0 | BC4: ='Absorption Schedule'!G57 -> 0 | BD4: ='Absorption Schedule'!G58 -> 0 | BE4: ='Absorption Schedule'!G59 -> 0 | BF4: ='Absorption Schedule'!G60 -> 0 | BG4: ='Absorption Schedule'!G61 -> 0 | BH4: ='Absorption Schedule'!G62 -> 0 | BI4: ='Absorption Schedule'!G63 -> 0
A5: Remaining Hard Costs | B5: =IF(B$3<='Market Assumptions'!$B$10,'Development Costs'!$B$14/'Market Assumptions'!$B$10,0) -> 0 | C5: =IF(C$3<='Market Assumptions'!$B$10,'Development Costs'!$B$14/'Market Assumptions'!$B$10,0) -> 0 | D5: =IF(D$3<='Market Assumptions'!$B$10,'Development Costs'!$B$14/'Market Assumptions'!$B$10,0) -> 0 | E5: =IF(E$3<='Market Assumptions'!$B$10,'Development Costs'!$B$14/'Market Assumptions'!$B$10,0) -> 0 | F5: =IF(F$3<='Market Assumptions'!$B$10,'Development Costs'!$B$14/'Market Assumptions'!$B$10,0) -> 0 | G5: =IF(G$3<='Market Assumptions'!$B$10,'Development Costs'!$B$14/'Market Assumptions'!$B$10,0) -> 0 | H5: =IF(H$3<='Market Assumptions'!$B$10,'Development Costs'!$B$14/'Market Assumptions'!$B$10,0) -> 0 | I5: =IF(I$3<='Market Assumptions'!$B$10,'Development Costs'!$B$14/'Market Assumptions'!$B$10,0) -> 0 | ... BI5: =IF(BI$3<='Market Assumptions'!$B$10,'Development Costs'!$B$14/'Market Assumptions'!$B$10,0) -> 0
A6: Remaining Soft Costs | B6: =IF(B$3<='Market Assumptions'!$B$11,'Development Costs'!$B$26/'Market Assumptions'!$B$11,0) -> 0 | C6: =IF(C$3<='Market Assumptions'!$B$11,'Development Costs'!$B$26/'Market Assumptions'!$B$11,0) -> 0 | D6: =IF(D$3<='Market Assumptions'!$B$11,'Development Costs'!$B$26/'Market Assumptions'!$B$11,0) -> 0 | E6: =IF(E$3<='Market Assumptions'!$B$11,'Development Costs'!$B$26/'Market Assumptions'!$B$11,0) -> 0 | F6: =IF(F$3<='Market Assumptions'!$B$11,'Development Costs'!$B$26/'Market Assumptions'!$B$11,0) -> 0 | G6: =IF(G$3<='Market Assumptions'!$B$11,'Development Costs'!$B$26/'Market Assumptions'!$B$11,0) -> 0 | H6: =IF(H$3<='Market Assumptions'!$B$11,'Development Costs'!$B$26/'Market Assumptions'!$B$11,0) -> 0 | I6: =IF(I$3<='Market Assumptions'!$B$11,'Development Costs'!$B$26/'Market Assumptions'!$B$11,0) -> 0 | ... BI6: =IF(BI$3<='Market Assumptions'!$B$11,'Development Costs'!$B$26/'Market Assumptions'!$B$11,0) -> 0
A7: Marketing & Selling Costs | B7: =B4*'Market Assumptions'!$B$7 -> 0 | C7: =C4*'Market Assumptions'!$B$7 -> 0 | D7: =D4*'Market Assumptions'!$B$7 -> 0 | E7: =E4*'Market Assumptions'!$B$7 -> 0 | F7: =F4*'Market Assumptions'!$B$7 -> 0 | G7: =G4*'Market Assumptions'!$B$7 -> 0 | H7: =H4*'Market Assumptions'!$B$7 -> 0 | I7: =I4*'Market Assumptions'!$B$7 -> 0 | ... BI7: =BI4*'Market Assumptions'!$B$7 -> 0
A8: Holding Costs | B8: =IF('Absorption Schedule'!C4>0,'Holding Costs'!$B$12,0) -> 0 | C8: =IF('Absorption Schedule'!C5>0,'Holding Costs'!$B$12,0) -> 0 | D8: =IF('Absorption Schedule'!C6>0,'Holding Costs'!$B$12,0) -> 0 | E8: =IF('Absorption Schedule'!C7>0,'Holding Costs'!$B$12,0) -> 0 | F8: =IF('Absorption Schedule'!C8>0,'Holding Costs'!$B$12,0) -> 0 | G8: =IF('Absorption Schedule'!C9>0,'Holding Costs'!$B$12,0) -> 0 | H8: =IF('Absorption Schedule'!C10>0,'Holding Costs'!$B$12,0) -> 0 | I8: =IF('Absorption Schedule'!C11>0,'Holding Costs'!$B$12,0) -> 0 | J8: =IF('Absorption Schedule'!C12>0,'Holding Costs'!$B$12,0) -> 0 | K8: =IF('Absorption Schedule'!C13>0,'Holding Costs'!$B$12,0) -> 0 | L8: =IF('Absorption Schedule'!C14>0,'Holding Costs'!$B$12,0) -> 0 | M8: =IF('Absorption Schedule'!C15>0,'Holding Costs'!$B$12,0) -> 0 | N8: =IF('Absorption Schedule'!C16>0,'Holding Costs'!$B$12,0) -> 0 | O8: =IF('Absorption Schedule'!C17>0,'Holding Costs'!$B$12,0) -> 0 | P8: =IF('Absorption Schedule'!C18>0,'Holding Costs'!$B$12,0) -> 0 | Q8: =IF('Absorption Schedule'!C19>0,'Holding Costs'!$B$12,0) -> 0 | R8: =IF('Absorption Schedule'!C20>0,'Holding Costs'!$B$12,0) -> 0 | S8: =IF('Absorption Schedule'!C21>0,'Holding Costs'!$B$12,0) -> 0 | T8: =IF('Absorption Schedule'!C22>0,'Holding Costs'!$B$12,0) -> 0 | U8: =IF('Absorption Schedule'!C23>0,'Holding Costs'!$B$12,0) -> 0 | V8: =IF('Absorption Schedule'!C24>0,'Holding Costs'!$B$12,0) -> 0 | W8: =IF('Absorption Schedule'!C25>0,'Holding Costs'!$B$12,0) -> 0 | X8: =IF('Absorption Schedule'!C26>0,'Holding Costs'!$B$12,0) -> 0 | Y8: =IF('Absorption Schedule'!C27>0,'Holding Costs'!$B$12,0) -> 0 | Z8: =IF('Absorption Schedule'!C28>0,'Holding Costs'!$B$12,0) -> 0 | AA8: =IF('Absorption Schedule'!C29>0,'Holding Costs'!$B$12,0) -> 0 | AB8: =IF('Absorption Schedule'!C30>0,'Holding Costs'!$B$12,0) -> 0 | AC8: =IF('Absorption Schedule'!C31>0,'Holding Costs'!$B$12,0) -> 0 | AD8: =IF('Absorption Schedule'!C32>0,'Holding Costs'!$B$12,0) -> 0 | AE8: =IF('Absorption Schedule'!C33>0,'Holding Costs'!$B$12,0) -> 0 | AF8: =IF('Absorption Schedule'!C34>0,'Holding Costs'!$B$12,0) -> 0 | AG8: =IF('Absorption Schedule'!C35>0,'Holding Costs'!$B$12,0) -> 0 | AH8: =IF('Absorption Schedule'!C36>0,'Holding Costs'!$B$12,0) -> 0 | AI8: =IF('Absorption Schedule'!C37>0,'Holding Costs'!$B$12,0) -> 0 | AJ8: =IF('Absorption Schedule'!C38>0,'Holding Costs'!$B$12,0) -> 0 | AK8: =IF('Absorption Schedule'!C39>0,'Holding Costs'!$B$12,0) -> 0 | AL8: =IF('Absorption Schedule'!C40>0,'Holding Costs'!$B$12,0) -> 0 | AM8: =IF('Absorption Schedule'!C41>0,'Holding Costs'!$B$12,0) -> 0 | AN8: =IF('Absorption Schedule'!C42>0,'Holding Costs'!$B$12,0) -> 0 | AO8: =IF('Absorption Schedule'!C43>0,'Holding Costs'!$B$12,0) -> 0 | AP8: =IF('Absorption Schedule'!C44>0,'Holding Costs'!$B$12,0) -> 0 | AQ8: =IF('Absorption Schedule'!C45>0,'Holding Costs'!$B$12,0) -> 0 | AR8: =IF('Absorption Schedule'!C46>0,'Holding Costs'!$B$12,0) -> 0 | AS8: =IF('Absorption Schedule'!C47>0,'Holding Costs'!$B$12,0) -> 0 | AT8: =IF('Absorption Schedule'!C48>0,'Holding Costs'!$B$12,0) -> 0 | AU8: =IF('Absorption Schedule'!C49>0,'Holding Costs'!$B$12,0) -> 0 | AV8: =IF('Absorption Schedule'!C50>0,'Holding Costs'!$B$12,0) -> 0 | AW8: =IF('Absorption Schedule'!C51>0,'Holding Costs'!$B$12,0) -> 0 | AX8: =IF('Absorption Schedule'!C52>0,'Holding Costs'!$B$12,0) -> 0 | AY8: =IF('Absorption Schedule'!C53>0,'Holding Costs'!$B$12,0) -> 0 | AZ8: =IF('Absorption Schedule'!C54>0,'Holding Costs'!$B$12,0) -> 0 | BA8: =IF('Absorption Schedule'!C55>0,'Holding Costs'!$B$12,0) -> 0 | BB8: =IF('Absorption Schedule'!C56>0,'Holding Costs'!$B$12,0) -> 0 | BC8: =IF('Absorption Schedule'!C57>0,'Holding Costs'!$B$12,0) -> 0 | BD8: =IF('Absorption Schedule'!C58>0,'Holding Costs'!$B$12,0) -> 0 | BE8: =IF('Absorption Schedule'!C59>0,'Holding Costs'!$B$12,0) -> 0 | BF8: =IF('Absorption Schedule'!C60>0,'Holding Costs'!$B$12,0) -> 0 | BG8: =IF('Absorption Schedule'!C61>0,'Holding Costs'!$B$12,0) -> 0 | BH8: =IF('Absorption Schedule'!C62>0,'Holding Costs'!$B$12,0) -> 0 | BI8: =IF('Absorption Schedule'!C63>0,'Holding Costs'!$B$12,0) -> 0
A9: Developer Profit / Incentive | B9: =B4*'Market Assumptions'!$B$8 -> 0 | C9: =C4*'Market Assumptions'!$B$8 -> 0 | D9: =D4*'Market Assumptions'!$B$8 -> 0 | E9: =E4*'Market Assumptions'!$B$8 -> 0 | F9: =F4*'Market Assumptions'!$B$8 -> 0 | G9: =G4*'Market Assumptions'!$B$8 -> 0 | H9: =H4*'Market Assumptions'!$B$8 -> 0 | I9: =I4*'Market Assumptions'!$B$8 -> 0 | ... BI9: =BI4*'Market Assumptions'!$B$8 -> 0
A10: Net Cash Flow | B10: =B4-SUM(B5:B9) -> 0 | C10: =C4-SUM(C5:C9) -> 0 | D10: =D4-SUM(D5:D9) -> 0 | E10: =E4-SUM(E5:E9) -> 0 | F10: =F4-SUM(F5:F9) -> 0 | G10: =G4-SUM(G5:G9) -> 0 | H10: =H4-SUM(H5:H9) -> 0 | I10: =I4-SUM(I5:I9) -> 0 | ... BI10: =BI4-SUM(BI5:BI9) -> 0
A11: Discount Factor | B11: =1/(1+'Discount Rate Support'!$C$13/12)^B$3 -> 1 | C11: =1/(1+'Discount Rate Support'!$C$13/12)^C$3 -> 1 | D11: =1/(1+'Discount Rate Support'!$C$13/12)^D$3 -> 1 | E11: =1/(1+'Discount Rate Support'!$C$13/12)^E$3 -> 1 | F11: =1/(1+'Discount Rate Support'!$C$13/12)^F$3 -> 1 | G11: =1/(1+'Discount Rate Support'!$C$13/12)^G$3 -> 1 | H11: =1/(1+'Discount Rate Support'!$C$13/12)^H$3 -> 1 | I11: =1/(1+'Discount Rate Support'!$C$13/12)^I$3 -> 1 | ... BI11: =1/(1+'Discount Rate Support'!$C$13/12)^BI$3 -> 1
A12: Present Value | B12: =B10*B11 -> 0 | C12: =C10*C11 -> 0 | D12: =D10*D11 -> 0 | E12: =E10*E11 -> 0 | F12: =F10*F11 -> 0 | G12: =G10*G11 -> 0 | H12: =H10*H11 -> 0 | I12: =I10*I11 -> 0 | ... BI12: =BI10*BI11 -> 0
A13: Cumulative Present Value | B13: =SUM($B$12:B12) -> 0 | C13: =SUM($B$12:C12) -> 0 | D13: =SUM($B$12:D12) -> 0 | E13: =SUM($B$12:E12) -> 0 | F13: =SUM($B$12:F12) -> 0 | G13: =SUM($B$12:G12) -> 0 | H13: =SUM($B$12:H12) -> 0 | I13: =SUM($B$12:I12) -> 0 | ... BI13: =SUM($B$12:BI12) -> 0
A16: DCF Summary
A17: Total Gross Revenue | B17: =SUM(B4:BI4) -> 0
A18: Total Hard Costs | B18: =SUM(B5:BI5) -> 0
A19: Total Soft Costs | B19: =SUM(B6:BI6) -> 0
A20: Total Marketing Costs | B20: =SUM(B7:BI7) -> 0
A21: Total Holding Costs | B21: =SUM(B8:BI8) -> 0
A22: Total Developer Profit | B22: =SUM(B9:BI9) -> 0
A23: DCF Present Value / Bulk Sale Value | B23: =SUM(B12:BI12) -> 0
A25: DCF model note: This model discounts monthly net cash flows derived from projected lot revenue, remaining hard and soft costs, marketing/selling costs, holding costs, and developer profit/incentive. Inputs must be supported in the appraisal report and retained in the workfile.

Sheet Bulk Sale Analysis
A1: Bulk Sale Analysis
A3: Bulk Sale Component | B3: Amount | C3: Notes
A4: Aggregate Retail Value | B4: =SUM('DCF Model'!B4:BI4) -> 0 | C4: Sum of projected gross revenue before deductions.
A5: Less: Remaining Hard Costs | B5: =SUM('DCF Model'!B5:BI5) -> 0 | C5: From DCF Model.
A6: Less: Remaining Soft Costs | B6: =SUM('DCF Model'!B6:BI6) -> 0 | C6: From DCF Model.
A7: Less: Marketing & Selling Costs | B7: =SUM('DCF Model'!B7:BI7) -> 0 | C7: From DCF Model.
A8: Less: Holding Costs | B8: =SUM('DCF Model'!B8:BI8) -> 0 | C8: From DCF Model.
A9: Less: Developer Profit / Incentive | B9: =SUM('DCF Model'!B9:BI9) -> 0 | C9: From DCF Model.
A10: Indicated Bulk Sale Value | B10: ='DCF Model'!B23 -> 0 | C10: Present value of net cash flows.
A11: Implied Bulk Sale Discount | B11: =IF(B4>0,1-B10/B4,0) -> 0 | C11: 1 - Bulk Sale Value / Aggregate Retail Value.
A12: Sellout Period | B12: =IFERROR(LOOKUP(2,1/('Absorption Schedule'!D4:D63>0),'Absorption Schedule'!A4:A63),0) -> 0 | C12: Last month with positive lot sales.
A13: Selected Discount Rate | B13: ='Discount Rate Support'!C13 -> 0 | C13: From Discount Rate Support.
A14: Monthly Absorption | B14: ='Market Assumptions'!B6 -> 0 | C14: From Market Assumptions.

Sheet Sensitivity Tables
A1: Sensitivity Tables
A3: Discount Rate Sensitivity
A4: Discount Rate | B4: Indicated Value
A5: -0.02 | B5: =SUMPRODUCT('DCF Model'!$B$10:$BI$10,1/(1+('Discount Rate Support'!$C$13+A5)/12)^'DCF Model'!$B$3:$BI$3) -> 0
A6: -0.01 | B6: =SUMPRODUCT('DCF Model'!$B$10:$BI$10,1/(1+('Discount Rate Support'!$C$13+A6)/12)^'DCF Model'!$B$3:$BI$3) -> 0
A7: 0 | B7: =SUMPRODUCT('DCF Model'!$B$10:$BI$10,1/(1+('Discount Rate Support'!$C$13+A7)/12)^'DCF Model'!$B$3:$BI$3) -> 0
A8: 0.01 | B8: =SUMPRODUCT('DCF Model'!$B$10:$BI$10,1/(1+('Discount Rate Support'!$C$13+A8)/12)^'DCF Model'!$B$3:$BI$3) -> 0
A9: 0.02 | B9: =SUMPRODUCT('DCF Model'!$B$10:$BI$10,1/(1+('Discount Rate Support'!$C$13+A9)/12)^'DCF Model'!$B$3:$BI$3) -> 0
A12: Sales Price Sensitivity
A13: Sales Price Change | B13: Indicated Value
A14: -0.1 | B14: =SUMPRODUCT(('DCF Model'!$B$4:$BI$4*(1+A14)-'DCF Model'!$B$5:$BI$5-'DCF Model'!$B$6:$BI$6-('DCF Model'!$B$4:$BI$4*(1+A14)*'Market Assumptions'!$B$7)-'DCF Model'!$B$8:$BI$8-('DCF Model'!$B$4:$BI$4*(1+A14)*'Market Assumptions'!$B$8)), 'DCF Model'!$B$11:$BI$11) -> 0
A15: -0.05 | B15: =SUMPRODUCT(('DCF Model'!$B$4:$BI$4*(1+A15)-'DCF Model'!$B$5:$BI$5-'DCF Model'!$B$6:$BI$6-('DCF Model'!$B$4:$BI$4*(1+A15)*'Market Assumptions'!$B$7)-'DCF Model'!$B$8:$BI$8-('DCF Model'!$B$4:$BI$4*(1+A15)*'Market Assumptions'!$B$8)), 'DCF Model'!$B$11:$BI$11) -> 0
A16: 0 | B16: =SUMPRODUCT(('DCF Model'!$B$4:$BI$4*(1+A16)-'DCF Model'!$B$5:$BI$5-'DCF Model'!$B$6:$BI$6-('DCF Model'!$B$4:$BI$4*(1+A16)*'Market Assumptions'!$B$7)-'DCF Model'!$B$8:$BI$8-('DCF Model'!$B$4:$BI$4*(1+A16)*'Market Assumptions'!$B$8)), 'DCF Model'!$B$11:$BI$11) -> 0
A17: 0.05 | B17: =SUMPRODUCT(('DCF Model'!$B$4:$BI$4*(1+A17)-'DCF Model'!$B$5:$BI$5-'DCF Model'!$B$6:$BI$6-('DCF Model'!$B$4:$BI$4*(1+A17)*'Market Assumptions'!$B$7)-'DCF Model'!$B$8:$BI$8-('DCF Model'!$B$4:$BI$4*(1+A17)*'Market Assumptions'!$B$8)), 'DCF Model'!$B$11:$BI$11) -> 0
A18: 0.1 | B18: =SUMPRODUCT(('DCF Model'!$B$4:$BI$4*(1+A18)-'DCF Model'!$B$5:$BI$5-'DCF Model'!$B$6:$BI$6-('DCF Model'!$B$4:$BI$4*(1+A18)*'Market Assumptions'!$B$7)-'DCF Model'!$B$8:$BI$8-('DCF Model'!$B$4:$BI$4*(1+A18)*'Market Assumptions'!$B$8)), 'DCF Model'!$B$11:$BI$11) -> 0
A21: Absorption Sensitivity
A22: Absorption Scenario | B22: Instruction | C22: Value
A23: Faster Absorption | B23: Increase Monthly Absorption in Market Assumptions by 20% and review DCF output.
A24: Base Case | B24: Current workbook case. | C24: ='Bulk Sale Analysis'!B11 -> 0
A25: Slower Absorption | B25: Decrease Monthly Absorption in Market Assumptions by 20% and review DCF output.
A26: Required Note | B26: Document whether absorption sensitivity was performed directly in this workbook or in an approved alternative model.
A27: Appraiser Comment

Sheet Report Exhibits
A1: Report Exhibits
A3: Exhibit Item | B3: Conclusion
A4: Property Name | B4: ='Property Info'!B4 -> 0
A5: Effective Date of Value | B5: ='Property Info'!B7 -> 46210
A6: Total Lots / Units | B6: ='Property Info'!B12 -> 0
A7: Monthly Absorption | B7: ='Market Assumptions'!B6 -> 0
A8: Sellout Period | B8: ='Bulk Sale Analysis'!B12 -> 0
A9: Aggregate Retail Value | B9: ='Bulk Sale Analysis'!B4 -> 0
A10: Selected Discount Rate | B10: ='Bulk Sale Analysis'!B13 -> 0
A11: DCF Present Value / Bulk Sale Value | B11: ='Bulk Sale Analysis'!B10 -> 0
A12: Implied Bulk Sale Discount | B12: ='Bulk Sale Analysis'!B11 -> 0
A13: Total Remaining Hard Costs | B13: ='Development Costs'!B14 -> 0
A14: Total Remaining Soft Costs | B14: ='Development Costs'!B26 -> 0
A15: Overall Sensitivity Reviewed | B15: Yes / No

Sheet Reviewer Checks
A1: Reviewer Checks
A3: Check | B3: Status | C3: Formula / Basis | D3: Reviewer Notes
A4: Property lot count entered | B4: =IF('Property Info'!B12>0,"OK","Missing") -> Missing | C4: Property Info!B12 > 0
A5: Beginning lot price entered | B5: =IF('Market Assumptions'!B4>0,"OK","Missing") -> Missing | C5: Market Assumptions!B4 > 0
A6: Monthly absorption entered | B6: =IF('Market Assumptions'!B6>0,"OK","Missing") -> Missing | C6: Market Assumptions!B6 > 0
A7: Discount rate selected | B7: =IF('Discount Rate Support'!C13>0,"OK","Missing") -> Missing | C7: Discount Rate Support!C13 > 0
A8: Hard cost support entered | B8: ="Reviewer" -> Reviewer | C8: Development Costs source column reviewed
A9: Soft cost support entered | B9: ="Reviewer" -> Reviewer | C9: Development Costs source column reviewed
A10: Holding costs reviewed | B10: ="Reviewer" -> Reviewer | C10: Holding Costs reviewed
A11: Bulk Sale Value calculated | B11: =IF('Bulk Sale Analysis'!B11<>0,"OK","Check") -> Check | C11: Bulk Sale Analysis!B11
A12: Sensitivity tables reviewed | B12: ="Reviewer" -> Reviewer | C12: Sensitivity Tables completed
A13: Workbook submitted with appraisal | B13: ="Reviewer" -> Reviewer | C13: Required by Chapter 8
A14: Appraiser narrative supports assumptions | B14: ="Reviewer" -> Reviewer | C14: Required in report
A15: No unexplained override formulas | B15: ="Reviewer" -> Reviewer | C15: Workbook review
A16: Reviewer conclusion | B16: ="Reviewer" -> Reviewer | C16: Pass / Revise / Reject
